{"version":1,"resource":"file:///home/hhouse/workspace/web_unlam/lab_front/src/components/AdminRetiroDevolucion.js","entries":[{"id":"PmbT.js","timestamp":1731004647793},{"id":"pfvP.js","timestamp":1731076694733},{"id":"T6Ud.js","timestamp":1731076712625},{"id":"qn5r.js","timestamp":1731076746948},{"id":"nG2Z.js","timestamp":1731076787120},{"id":"elkx.js","source":"undoRedo.source","timestamp":1731076795084},{"id":"d9ZZ.js","timestamp":1731076800148},{"id":"ylgz.js","source":"undoRedo.source","timestamp":1731076802632},{"id":"nXEp.js","timestamp":1731076812819},{"id":"TVL2.js","timestamp":1731076827563},{"id":"wrEV.js","timestamp":1731076852691},{"id":"NHY9.js","timestamp":1731076869490},{"id":"Sk9J.js","timestamp":1731076956313},{"id":"MbSr.js","timestamp":1731076984729},{"id":"Y3Py.js","timestamp":1731077020160},{"id":"Stcv.js","timestamp":1731077077020},{"id":"1r3I.js","timestamp":1731077185066},{"id":"xRVq.js","timestamp":1731077251097},{"id":"DOKX.js","source":"undoRedo.source","timestamp":1731087804160},{"id":"N4Mo.js","timestamp":1731613543787},{"id":"cO2w.js","source":"undoRedo.source","timestamp":1731613548219}]}